pybae/__init__.py
pybae/config.py
pybae/utils/__init__.py
pybae/utils/datetools.py
pybae-0.1.7.dist-info/licenses/LICENSE
pybae-0.1.7.dist-info/METADATA
pybae-0.1.7.dist-info/WHEEL
pybae-0.1.7.dist-info/top_level.txt
pybae-0.1.7.dist-info/RECORD
