Metadata-Version: 2.4
Name: pybae
Version: 0.1.7
Summary: Core utilities for backend applications
Author-email: zangico <zangico@gmail.com>
License: MIT
Project-URL: Homepage, https://github.com/zangico/pybae
Project-URL: Repository, https://github.com/zangico/pybae
Project-URL: Documentation, https://github.com/zangico/pybae#readme
Project-URL: Bug Tracker, https://github.com/zangico/pybae/issues
Keywords: backend,configuration,utilities,pydantic,dotenv
Classifier: Development Status :: 3 - Alpha
Classifier: Intended Audience :: Developers
Classifier: License :: OSI Approved :: MIT License
Classifier: Programming Language :: Python :: 3
Requires-Python: >=3.11
License-File: LICENSE
Requires-Dist: pydantic>=2.0.0
Requires-Dist: python-dotenv>=1.0.0
Provides-Extra: dev
Requires-Dist: black; extra == "dev"
Requires-Dist: isort; extra == "dev"
Requires-Dist: mypy; extra == "dev"
Requires-Dist: ruff; extra == "dev"
Dynamic: license-file
